squill/__init__.py
squill-0.0.0.dist-info/LICENSE
squill-0.0.0.dist-info/METADATA
squill-0.0.0.dist-info/WHEEL
squill-0.0.0.dist-info/top_level.txt
squill-0.0.0.dist-info/RECORD
