Metadata-Version: 2.1
Name: squill
Version: 0.0.0
Summary: Tool for managing database revisions
License: BSD-3-Clause
License-File: LICENSE
